harlequin_odbc/__init__.py
harlequin_odbc/adapter.py
harlequin_odbc/catalog.py
harlequin_odbc/cli_options.py
harlequin_odbc/interactions.py
harlequin_odbc/py.typed
harlequin_odbc-0.3.1.dist-info/LICENSE
harlequin_odbc-0.3.1.dist-info/METADATA
harlequin_odbc-0.3.1.dist-info/WHEEL
harlequin_odbc-0.3.1.dist-info/entry_points.txt
harlequin_odbc-0.3.1.dist-info/RECORD
