Metadata-Version: 2.1
Name: harlequin-odbc
Version: 0.3.1
Summary: A Harlequin adapter for ODBC drivers.
License: MIT
Author: Ted Conbeer
Author-email: tconbeer@users.noreply.github.com
Requires-Python: >=3.9,<3.14
Classifier: License :: OSI Approved :: MIT License
Classifier: Programming Language :: Python :: 3
Classifier: Programming Language :: Python :: 3.9
Classifier: Programming Language :: Python :: 3.10
Classifier: Programming Language :: Python :: 3.11
Requires-Dist: harlequin (>=1.25,<3)
Requires-Dist: pyodbc (>=5.0,<6.0)
